MANIFEST.in
README.rst
setup.py
boto_utils/__init__.py
boto_utils/cloudwatch-put-metric
boto_utils/common.py
boto_utils/s3-copy
boto_utils/s3-delete
boto_utils/s3-geturl
boto_utils/s3-put
boto_utils/ses-send-email
boto_utils/ses-verify-email-address
boto_utils/ses.py
boto_utils.egg-info/PKG-INFO
boto_utils.egg-info/SOURCES.txt
boto_utils.egg-info/dependency_links.txt
boto_utils.egg-info/requires.txt
boto_utils.egg-info/top_level.txt