Metadata-Version: 1.0
Name: boto-utils
Version: 0.3
Summary: Command-line tools based on Boto
Home-page: https://github.com/obeattie/boto_utils
Author: Oliver Beattie
Author-email: oliver@obeattie.com
License: UNKNOWN
Platform: UNKNOWN
Classifier: Development Status :: 2 - Pre-Alpha
Classifier: Environment :: Console
Classifier: Intended Audience :: Developers
Classifier: Intended Audience :: System Administrators
Classifier: License :: OSI Approved :: GNU General Public License (GPL)
Classifier: Programming Language :: Python :: 2.7
Classifier: Topic :: Utilities
